djangocms_oidc_form_fields/__init__.py
djangocms_oidc_form_fields/action_backends.py
djangocms_oidc_form_fields/admin.py
djangocms_oidc_form_fields/apps.py
djangocms_oidc_form_fields/cms_plugins.py
djangocms_oidc_form_fields/constants.py
djangocms_oidc_form_fields/forms.py
djangocms_oidc_form_fields/models.py
djangocms_oidc_form_fields/locale/cs/LC_MESSAGES/django.mo
djangocms_oidc_form_fields/locale/cs/LC_MESSAGES/django.po
djangocms_oidc_form_fields/migrations/0001_initial.py
djangocms_oidc_form_fields/migrations/0002_oidcformsubmission.py
djangocms_oidc_form_fields/migrations/0003_oidcelementplugin_and_more.py
djangocms_oidc_form_fields/migrations/0004_oidcformsubmission_honeypot_filled_and_more.py
djangocms_oidc_form_fields/migrations/__init__.py
djangocms_oidc_form_fields/templates/djangocms_oidc_form_fields/span.html
djangocms_oidc_form_fields/templates/djangocms_oidc_form_fields/emails/notification.body.html
djangocms_oidc_form_fields/templates/djangocms_oidc_form_fields/emails/notification.body.txt
djangocms_oidc_form_fields/templates/djangocms_oidc_form_fields/emails/includes/user_info_data.html
djangocms_oidc_form_fields/templates/djangocms_oidc_form_fields/emails/includes/user_info_data.txt
djangocms_oidc_form_fields-4.1.0.dist-info/licenses/LICENSE
djangocms_oidc_form_fields-4.1.0.dist-info/METADATA
djangocms_oidc_form_fields-4.1.0.dist-info/WHEEL
djangocms_oidc_form_fields-4.1.0.dist-info/top_level.txt
djangocms_oidc_form_fields-4.1.0.dist-info/RECORD
